deepmolecules/__init__.py
deepmolecules/_chem.py
deepmolecules/_download.py
deepmolecules/_shared_paths.py
deepmolecules/py.typed
deepmolecules/kcat/__init__.py
deepmolecules/kcat/_paths.py
deepmolecules/km/__init__.py
deepmolecules/km/_constants.py
deepmolecules/km/_paths.py
deepmolecules-0.1.0.dist-info/METADATA
deepmolecules-0.1.0.dist-info/WHEEL
deepmolecules-0.1.0.dist-info/licenses/LICENSE
deepmolecules-0.1.0.dist-info/RECORD
