Metadata-Version: 2.4
Name: deepmolecules
Version: 0.1.0
Summary: Prediction of enzyme kinetic parameters using deep learning models
Project-URL: Changelog, https://gitlab.com/marvin.vanaalst/deepmolecules/changelog.rst
Project-URL: Documentation, https://deepmolecules.gitlab.io/mkdocs/
Project-URL: Homepage, https://gitlab.com/marvin.vanaalst/deepmolecules
Project-URL: Issues, https://gitlab.com/marvin.vanaalst/deepmolecules/-/issues
Project-URL: Repository, https://gitlab.com/marvin.vanaalst/deepmolecules.git
Author-email: Marvin van Aalst <marvin.vanaalst@gmail.com>, Yvan Rousset <yvan.rousset@hhu.de>, Alexander Kroll <alexander.kroll@hhu.de>
License:                     GNU GENERAL PUBLIC LICENSE
License-File: LICENSE
Keywords: ai,enzyme,kinetics,machine learning
Classifier: Programming Language :: Python :: 3.11
Requires-Python: <3.13,>=3.11
Requires-Dist: fair-esm>=2.0.0
Requires-Dist: pandas>=2.2.3
Requires-Dist: rdkit>=2024.3.6
Requires-Dist: tensorflow<2.16.0
Requires-Dist: torch>=2.5.1
Requires-Dist: tqdm>=4.67.1
Requires-Dist: xgboost>=2.1.3
Provides-Extra: dev
Requires-Dist: coverage>=7.6.4; extra == 'dev'
Requires-Dist: jupyter>=1.1.1; extra == 'dev'
Requires-Dist: mkdocs-jupyter>=0.25.1; extra == 'dev'
Requires-Dist: mkdocs-material>=9.5.42; extra == 'dev'
Requires-Dist: mkdocs>=1.6.1; extra == 'dev'
Requires-Dist: mypy>=1.13.0; extra == 'dev'
Requires-Dist: pre-commit>=4.0.1; extra == 'dev'
Requires-Dist: pyright>=1.1.387; extra == 'dev'
Requires-Dist: pytest-cov>=5.0.0; extra == 'dev'
Requires-Dist: pytest>=8.3.3; extra == 'dev'
Requires-Dist: requests>=2.32.3; extra == 'dev'
Requires-Dist: ruff>=0.7.1; extra == 'dev'
Requires-Dist: ssort>=0.13.0; extra == 'dev'
Requires-Dist: toml-sort<0.24,>=0.23.1; extra == 'dev'
